<?xml version="1.0"?>
<options>
  <models>
    <!-- <model baseDir="..\Models\">SphereOnly.obj</model> -->
    <!-- <model baseDir="..\Models\">CornellBox-Sphere.obj</model>     -->
  </models>
  <!-- <densityField baseDir="..\DensityFields\">fire.nvdb</densityField> -->
  <densityField baseDir="..\DensityFields\">bunny_cloud.nvdb</densityField>
  <sigma_a>0.2</sigma_a>
  <sigma_s>1.0</sigma_s>
  <heyneygreenstein_g>0</heyneygreenstein_g>
  <rayPerPixelCount>4</rayPerPixelCount>
  <maxDepth>4</maxDepth>
  <integrator>deltaTracking</integrator>  
	<width startOffset="0" reference="640">640</width>
	<!-- <height startOffset="0" reference="640">16</height> -->
  <!-- <width startOffset="160" reference="640">320</width> -->
	<height startOffset="0" reference="640">640</height>
	<multiThreaded>true</multiThreaded>
  <!-- determinism is guaranteed as long as multiThreadedChunkSize doesn't change from execution to execution -->
  <multiThreadedChunkSize>16</multiThreadedChunkSize>

	<!-- pitch: x, crece hacia arriba, yaw: y, crece para la izquierda, roll: z, crece en sentido antihorario -->
	<!-- camera for sphere -->
  <!-- <camera x="0" y="0.825" z="6.75" pitch="0" yaw="0" roll="0" fov="60"/> -->
  <!-- camera for bunny_cloud.nvdb -->
  <camera x="-15.5" y="40.5" z="-54.0" pitch="-20.0" yaw="190.0" roll="0.0" fov="50"/>
  <!-- camera for fire.nvdb -->
  <!-- <camera x="-1.0" y="40" z="75.0" pitch="0" yaw="0" roll="0" fov="80"/> -->

  <backgroundColor r="0.572" g="0.772" b="0.921"/> 
 
  <!-- 60 times more than above -->
  <light x="0" y="1" z="0" r="19.65" g="4.5" b="13.5" multiplier="0.05"/>
  <emission r="0.25" g="0.125" b="0.025" multiplier="0.3"/>
</options>
